napari_ptufile/__init__.py
napari_ptufile-0.0.3.dist-info/METADATA
napari_ptufile-0.0.3.dist-info/WHEEL
napari_ptufile-0.0.3.dist-info/entry_points.txt
napari_ptufile-0.0.3.dist-info/top_level.txt
napari_ptufile-0.0.3.dist-info/RECORD
