Metadata-Version: 2.1
Name: napari-ptufile
Version: 0.0.3
Summary: A napari plugin for reading files via ptufile
Home-page: https://pypi.org/project/{name}/
Author: Christoph Gohlke
Author-email: cgohlke@cgohlke.com
License: BSD
Project-URL: Bug Tracker, https://github.com/cgohlke/ptufile/issues
Project-URL: Source Code, https://github.com/cgohlke/ptufile
Platform: any
Classifier: Development Status :: 3 - Alpha
Classifier: License :: OSI Approved :: BSD License
Classifier: Intended Audience :: Science/Research
Classifier: Operating System :: OS Independent
Classifier: Programming Language :: Python :: 3 :: Only
Classifier: Programming Language :: Python :: 3.9
Classifier: Programming Language :: Python :: 3.10
Classifier: Programming Language :: Python :: 3.11
Classifier: Programming Language :: Python :: 3.12
Requires-Python: >=3.9
Requires-Dist: ptufile
